{
	"files_path": {
		"cover_train_path": "/home/user/data/audio/QMDCT/cover/cover_10s/128/train",
        "cover_valid_path": "/home/user/data/audio/QMDCT/cover/cover_10s/128/validation",
        "stego_train_path": "/home/user/data/audio/QMDCT/stego/EECS/EECS_B_128_W_2_H_7_ER_10/train",
        "stego_valid_path": "/home/user/data/audio/QMDCT/stego/EECS/EECS_B_128_W_2_H_7_ER_10/validation",
        "model_path": "/home/user/code/CatKing/steganalysis_CNN/models/steganalysis",
        "log_path": "/home/user/code/CatKing/steganalysis_CNN/logs/steganalysis",
        "model_file_name": "down_sampling"
    },
    "index": {
        "start_index_train": null,
        "end_index_train": null,
        "start_index_valid": null,
        "end_index_valid": null
    },
	"mode_config": {
		"gpu_selection": "None",
        "gpu": "0",
        "mode": "train",
        "carrier": "audio",
        "network": "downsampling_network"
    },
    "hyper_parameters": {
        "batch_size_train": 64,
        "batch_size_valid": 16,
        "learning_rate": 0.001,
        "epoch": 500,
        "seed": 1,
        "is_regulation": true,
        "coeff_regulation": 0.001,
        "loss_method": "sparse_softmax_cross_entropy",
        "class_num": 2
    },
    "preprocessing_method": {
        "height": 200,
        "width": 450,
        "channel": 1,
        "is_abs": false,
        "is_trunc": false,
        "is_diff": false,
        "is_diff_abs": false,
        "is_abs_diff": false,
        "threshold": 15,
        "order": 0,
        "direction": 0
    },
    "learning_rate_method":{
        "decay_method": "exponential",
        "decay_step": 5000,
        "decay_rate": 0.9,
        "staircase": false
    },
    "model": {
        "max_to_keep": 3,
        "keep_checkpoint_every_n_hours": 0.5
    }
}